{
  "tarefas": [
    {
      "nome": "Atividada prática SM 12",
      "status": 1,
      "data": "2024-05-19T14:56:00.000Z",
      "materiaId": 2,
      "prioridade": 3,
      "descricao": "Entragar atividade de DIW",
      "id": 1
    },
    {
      "id": "70b7",
      "nome": "Resumo livro",
      "status": 1,
      "data": "2024-06-02T14:56:00.000Z",
      "materiaId": 2,
      "prioridade": 1,
      "descricao": "Entregar atividade"
    }
  ],
  "materias": [
    {
      "id": 1,
      "nome": "TIAW"
    },
    {
      "id": 2,
      "nome": "DIW"
    },
    {
      "id": 3,
      "nome": "ATP"
    },
    {
      "id": 4,
      "nome": "Filosofia"
    },
    {
      "id": 5,
      "nome": "Introdução a computação"
    }
  ]
}
